LICENSE
MANIFEST.in
README.md
setup.cfg
setup.py
tap_listrak/__init__.py
tap_listrak/client.py
tap_listrak/discover.py
tap_listrak/schema.py
tap_listrak/sync.py
tap_listrak.egg-info/PKG-INFO
tap_listrak.egg-info/SOURCES.txt
tap_listrak.egg-info/dependency_links.txt
tap_listrak.egg-info/entry_points.txt
tap_listrak.egg-info/requires.txt
tap_listrak.egg-info/top_level.txt
tap_listrak/schemas/campaigns.json
tap_listrak/schemas/contacts.json
tap_listrak/schemas/conversation_message_activity.json
tap_listrak/schemas/conversation_messages.json
tap_listrak/schemas/conversations.json
tap_listrak/schemas/lists.json
tap_listrak/schemas/message_activity.json
tap_listrak/schemas/message_link_clickers.json
tap_listrak/schemas/message_links.json
tap_listrak/schemas/messages.json
tap_listrak/schemas/transactional_messages.json