Metadata-Version: 1.1
Name: tap-listrak
Version: 2.0.8
Summary: Singer.io tap for extracting data from the Listrak API
Home-page: https://singer.io
Author: Stitch
Author-email: UNKNOWN
License: UNKNOWN
Platform: UNKNOWN
Classifier: Programming Language :: Python :: 3 :: Only
